{
    "asset": {
        "id": "76dbd783266b0600faab53a988ad6973",
        "format": "533333",
        "state": 2,
        "type": 3,
        "name": "2670789134335610222_267650658.mp4#t=3.533333",
        "path": "file://wsl.localhost/Debian/root/workspace/bar_tracking/training/video/2670789134335610222_267650658.mp4#t=3.533333",
        "size": {
            "width": 720,
            "height": 720
        },
        "parent": {
            "format": "mp4",
            "id": "8fc840b26e701c4581d5190c53450499",
            "name": "2670789134335610222_267650658.mp4",
            "path": "file://wsl.localhost/Debian/root/workspace/bar_tracking/training/video/2670789134335610222_267650658.mp4",
            "size": {
                "width": 720,
                "height": 720
            },
            "state": 1,
            "type": 2
        },
        "timestamp": 3.533333
    },
    "regions": [
        {
            "id": "mc1V03FTS",
            "type": "RECTANGLE",
            "tags": [
                "bar_end"
            ],
            "boundingBox": {
                "height": 19.646869983948637,
                "width": 15.601926163723917,
                "left": 111.81380417335474,
                "top": 190.69020866773675
            },
            "points": [
                {
                    "x": 111.81380417335474,
                    "y": 190.69020866773675
                },
                {
                    "x": 127.41573033707866,
                    "y": 190.69020866773675
                },
                {
                    "x": 127.41573033707866,
                    "y": 210.3370786516854
                },
                {
                    "x": 111.81380417335474,
                    "y": 210.3370786516854
                }
            ]
        },
        {
            "id": "t6wKP81mk",
            "type": "RECTANGLE",
            "tags": [
                "outside_plate"
            ],
            "boundingBox": {
                "height": 176.24398073836278,
                "width": 153.70786516853934,
                "left": 87.54414125200643,
                "top": 117.30337078651687
            },
            "points": [
                {
                    "x": 87.54414125200643,
                    "y": 117.30337078651687
                },
                {
                    "x": 241.25200642054577,
                    "y": 117.30337078651687
                },
                {
                    "x": 241.25200642054577,
                    "y": 293.5473515248796
                },
                {
                    "x": 87.54414125200643,
                    "y": 293.5473515248796
                }
            ]
        },
        {
            "id": "p4DYiEH3C",
            "type": "RECTANGLE",
            "tags": [
                "inside_plate"
            ],
            "boundingBox": {
                "height": 160.64205457463885,
                "width": 143.88443017656502,
                "left": 357.97752808988764,
                "top": 159.48635634028892
            },
            "points": [
                {
                    "x": 357.97752808988764,
                    "y": 159.48635634028892
                },
                {
                    "x": 501.8619582664527,
                    "y": 159.48635634028892
                },
                {
                    "x": 501.8619582664527,
                    "y": 320.12841091492777
                },
                {
                    "x": 357.97752808988764,
                    "y": 320.12841091492777
                }
            ]
        }
    ],
    "version": "2.2.0"
}