{
    "asset": {
        "format": "jpg",
        "id": "3d84abf5efcfcb1f726720a11ca02c49",
        "name": "outside_plate-88428574100.jpg",
        "path": "file://wsl.localhost/Debian/root/workspace/bar_tracking/training/plate_images/images/outside_plate-88428574100.jpg",
        "size": {
            "width": 128,
            "height": 128
        },
        "state": 2,
        "type": 1
    },
    "regions": [
        {
            "id": "t0xr65Vgj",
            "type": "RECTANGLE",
            "tags": [
                "center"
            ],
            "boundingBox": {
                "height": 0,
                "width": 0,
                "left": 73.88087774294671,
                "top": 68.31347962382445
            },
            "points": [
                {
                    "x": 73.88087774294671,
                    "y": 68.31347962382445
                },
                {
                    "x": 73.88087774294671,
                    "y": 68.31347962382445
                },
                {
                    "x": 73.88087774294671,
                    "y": 68.31347962382445
                },
                {
                    "x": 73.88087774294671,
                    "y": 68.31347962382445
                }
            ]
        }
    ],
    "version": "2.2.0"
}