{
    "asset": {
        "format": "jpg",
        "id": "6d139b8083630ce1bfc331f762c46d1a",
        "name": "inside_plate-52577746800.jpg",
        "path": "file://wsl.localhost/Debian/root/workspace/bar_tracking/training/plate_images/images/inside_plate-52577746800.jpg",
        "size": {
            "width": 128,
            "height": 128
        },
        "state": 2,
        "type": 1
    },
    "regions": [
        {
            "id": "q1BIP2d1V",
            "type": "RECTANGLE",
            "tags": [
                "center"
            ],
            "boundingBox": {
                "height": 0,
                "width": 0,
                "left": 71.47335423197492,
                "top": 44.539184952978054
            },
            "points": [
                {
                    "x": 71.47335423197492,
                    "y": 44.539184952978054
                },
                {
                    "x": 71.47335423197492,
                    "y": 44.539184952978054
                },
                {
                    "x": 71.47335423197492,
                    "y": 44.539184952978054
                },
                {
                    "x": 71.47335423197492,
                    "y": 44.539184952978054
                }
            ]
        }
    ],
    "version": "2.2.0"
}