{
    "asset": {
        "format": "jpg",
        "id": "b1956df79a39e736b5377253836e70f0",
        "name": "outside_plate-64246465500.jpg",
        "path": "file://wsl.localhost/Debian/root/workspace/bar_tracking/training/plate_images/images/outside_plate-64246465500.jpg",
        "size": {
            "width": 128,
            "height": 128
        },
        "state": 2,
        "type": 1
    },
    "regions": [
        {
            "id": "gObD4ZYJ0",
            "type": "RECTANGLE",
            "tags": [
                "center"
            ],
            "boundingBox": {
                "height": 0,
                "width": 0,
                "left": 75.0846394984326,
                "top": 77.141065830721
            },
            "points": [
                {
                    "x": 75.0846394984326,
                    "y": 77.141065830721
                },
                {
                    "x": 75.0846394984326,
                    "y": 77.141065830721
                },
                {
                    "x": 75.0846394984326,
                    "y": 77.141065830721
                },
                {
                    "x": 75.0846394984326,
                    "y": 77.141065830721
                }
            ]
        }
    ],
    "version": "2.2.0"
}