{
    "asset": {
        "format": "jpg",
        "id": "fa4cfc9f19a5f4ecf23a2e0452681d94",
        "name": "outside_plate-18153557100.jpg",
        "path": "file://wsl.localhost/Debian/root/workspace/bar_tracking/training/plate_images/images/outside_plate-18153557100.jpg",
        "size": {
            "width": 128,
            "height": 128
        },
        "state": 2,
        "type": 1
    },
    "regions": [
        {
            "id": "UMH-_ci9S",
            "type": "RECTANGLE",
            "tags": [
                "center"
            ],
            "boundingBox": {
                "height": 0,
                "width": 0,
                "left": 51.7115987460815,
                "top": 61.59247648902821
            },
            "points": [
                {
                    "x": 51.7115987460815,
                    "y": 61.59247648902821
                },
                {
                    "x": 51.7115987460815,
                    "y": 61.59247648902821
                },
                {
                    "x": 51.7115987460815,
                    "y": 61.59247648902821
                },
                {
                    "x": 51.7115987460815,
                    "y": 61.59247648902821
                }
            ]
        }
    ],
    "version": "2.2.0"
}