{
    "asset": {
        "format": "jpg",
        "id": "2018f389d31e85c44387a067948b0602",
        "name": "33443107100.jpg",
        "path": "file://wsl.localhost/Debian/root/workspace/bar_tracking/training/training_images/33443107100.jpg",
        "size": {
            "width": 720,
            "height": 720
        },
        "state": 2,
        "type": 1
    },
    "regions": [
        {
            "id": "g5InI9QnJ",
            "type": "RECTANGLE",
            "tags": [
                "outside_plate"
            ],
            "boundingBox": {
                "height": 195.79937304075233,
                "width": 182.82131661442006,
                "left": 475.39184952978053,
                "top": 0
            },
            "points": [
                {
                    "x": 475.39184952978053,
                    "y": 0
                },
                {
                    "x": 658.2131661442006,
                    "y": 0
                },
                {
                    "x": 658.2131661442006,
                    "y": 195.79937304075233
                },
                {
                    "x": 475.39184952978053,
                    "y": 195.79937304075233
                }
            ]
        },
        {
            "id": "ctrnBCYQB",
            "type": "RECTANGLE",
            "tags": [
                "inside_plate"
            ],
            "boundingBox": {
                "height": 205.39184952978056,
                "width": 177.74294670846393,
                "left": 88.30721003134795,
                "top": 90.282131661442
            },
            "points": [
                {
                    "x": 88.30721003134795,
                    "y": 90.282131661442
                },
                {
                    "x": 266.0501567398119,
                    "y": 90.282131661442
                },
                {
                    "x": 266.0501567398119,
                    "y": 295.67398119122254
                },
                {
                    "x": 88.30721003134795,
                    "y": 295.67398119122254
                }
            ]
        }
    ],
    "version": "2.2.0"
}