{
    "asset": {
        "format": "jpg",
        "id": "2448362de77501821e825709bc7f72d6",
        "name": "50386925100.jpg",
        "path": "file://wsl.localhost/Debian/root/workspace/bar_tracking/training/training_images/50386925100.jpg",
        "size": {
            "width": 720,
            "height": 720
        },
        "state": 2,
        "type": 1
    },
    "regions": [
        {
            "id": "sx8h9BwBt",
            "type": "RECTANGLE",
            "tags": [
                "inside_plate"
            ],
            "boundingBox": {
                "height": 84.54193548387097,
                "width": 104.98064516129033,
                "left": 558.3483870967742,
                "top": 418.9935483870968
            },
            "points": [
                {
                    "x": 558.3483870967742,
                    "y": 418.9935483870968
                },
                {
                    "x": 663.3290322580646,
                    "y": 418.9935483870968
                },
                {
                    "x": 663.3290322580646,
                    "y": 503.53548387096777
                },
                {
                    "x": 558.3483870967742,
                    "y": 503.53548387096777
                }
            ]
        },
        {
            "id": "D8u6rhbj8",
            "type": "RECTANGLE",
            "tags": [
                "outside_plate"
            ],
            "boundingBox": {
                "height": 104.05161290322582,
                "width": 89.18709677419355,
                "left": 111.48387096774194,
                "top": 501.6774193548387
            },
            "points": [
                {
                    "x": 111.48387096774194,
                    "y": 501.6774193548387
                },
                {
                    "x": 200.6709677419355,
                    "y": 501.6774193548387
                },
                {
                    "x": 200.6709677419355,
                    "y": 605.7290322580645
                },
                {
                    "x": 111.48387096774194,
                    "y": 605.7290322580645
                }
            ]
        }
    ],
    "version": "2.2.0"
}