{
    "asset": {
        "format": "jpg",
        "id": "2782b89914a6c9c97b087bdae572ce4d",
        "name": "69927581900.jpg",
        "path": "file://wsl.localhost/Debian/root/workspace/bar_tracking/training/training_images/69927581900.jpg",
        "size": {
            "width": 720,
            "height": 720
        },
        "state": 2,
        "type": 1
    },
    "regions": [
        {
            "id": "B7d0WVnES",
            "type": "RECTANGLE",
            "tags": [
                "inside_plate"
            ],
            "boundingBox": {
                "height": 160.81504702194357,
                "width": 158.5579937304075,
                "left": 326.4263322884012,
                "top": 196.36363636363635
            },
            "points": [
                {
                    "x": 326.4263322884012,
                    "y": 196.36363636363635
                },
                {
                    "x": 484.98432601880876,
                    "y": 196.36363636363635
                },
                {
                    "x": 484.98432601880876,
                    "y": 357.1786833855799
                },
                {
                    "x": 326.4263322884012,
                    "y": 357.1786833855799
                }
            ]
        },
        {
            "id": "RMph1IFDC",
            "type": "RECTANGLE",
            "tags": [
                "outside_plate"
            ],
            "boundingBox": {
                "height": 177.17868338557992,
                "width": 169.27899686520374,
                "left": 123.85579937304074,
                "top": 232.47648902821314
            },
            "points": [
                {
                    "x": 123.85579937304074,
                    "y": 232.47648902821314
                },
                {
                    "x": 293.13479623824446,
                    "y": 232.47648902821314
                },
                {
                    "x": 293.13479623824446,
                    "y": 409.6551724137931
                },
                {
                    "x": 123.85579937304074,
                    "y": 409.6551724137931
                }
            ]
        }
    ],
    "version": "2.2.0"
}