{
    "asset": {
        "format": "jpg",
        "id": "2c656c5d1ae0cc0add989661a1f43363",
        "name": "83108882600.jpg",
        "path": "file://wsl.localhost/Debian/root/workspace/bar_tracking/training/training_images/83108882600.jpg",
        "size": {
            "width": 720,
            "height": 720
        },
        "state": 2,
        "type": 1
    },
    "regions": [
        {
            "id": "0EL8bkD0G",
            "type": "RECTANGLE",
            "tags": [
                "outside_plate"
            ],
            "boundingBox": {
                "height": 218.3699059561128,
                "width": 204.54545454545448,
                "left": 115.67398119122257,
                "top": 0
            },
            "points": [
                {
                    "x": 115.67398119122257,
                    "y": 0
                },
                {
                    "x": 320.21943573667704,
                    "y": 0
                },
                {
                    "x": 320.21943573667704,
                    "y": 218.3699059561128
                },
                {
                    "x": 115.67398119122257,
                    "y": 218.3699059561128
                }
            ]
        },
        {
            "id": "Z1MYNCfQy",
            "type": "RECTANGLE",
            "tags": [
                "inside_plate"
            ],
            "boundingBox": {
                "height": 195.2351097178683,
                "width": 181.69278996865202,
                "left": 422.91536050156736,
                "top": 113.98119122257052
            },
            "points": [
                {
                    "x": 422.91536050156736,
                    "y": 113.98119122257052
                },
                {
                    "x": 604.6081504702194,
                    "y": 113.98119122257052
                },
                {
                    "x": 604.6081504702194,
                    "y": 309.2163009404388
                },
                {
                    "x": 422.91536050156736,
                    "y": 309.2163009404388
                }
            ]
        }
    ],
    "version": "2.2.0"
}