{
    "asset": {
        "format": "jpg",
        "id": "3ce4fb27c1c62bd0dc4a24b7f66242df",
        "name": "59106327700.jpg",
        "path": "file://wsl.localhost/Debian/root/workspace/bar_tracking/training/training_images/59106327700.jpg",
        "size": {
            "width": 720,
            "height": 720
        },
        "state": 2,
        "type": 1
    },
    "regions": [
        {
            "id": "2REeCBY8Y",
            "type": "RECTANGLE",
            "tags": [
                "outside_plate"
            ],
            "boundingBox": {
                "height": 120.7741935483871,
                "width": 130.99354838709678,
                "left": 0,
                "top": 494.2451612903226
            },
            "points": [
                {
                    "x": 0,
                    "y": 494.2451612903226
                },
                {
                    "x": 130.99354838709678,
                    "y": 494.2451612903226
                },
                {
                    "x": 130.99354838709678,
                    "y": 615.0193548387097
                },
                {
                    "x": 0,
                    "y": 615.0193548387097
                }
            ]
        },
        {
            "id": "weIMCNZ0j",
            "type": "RECTANGLE",
            "tags": [
                "inside_plate"
            ],
            "boundingBox": {
                "height": 100.33548387096775,
                "width": 139.35483870967744,
                "left": 410.6322580645161,
                "top": 546.2709677419355
            },
            "points": [
                {
                    "x": 410.6322580645161,
                    "y": 546.2709677419355
                },
                {
                    "x": 549.9870967741936,
                    "y": 546.2709677419355
                },
                {
                    "x": 549.9870967741936,
                    "y": 646.6064516129032
                },
                {
                    "x": 410.6322580645161,
                    "y": 646.6064516129032
                }
            ]
        }
    ],
    "version": "2.2.0"
}