{
    "asset": {
        "format": "jpg",
        "id": "441d0a0026797e4485ef71246b324018",
        "name": "21321464700.jpg",
        "path": "file://wsl.localhost/Debian/root/workspace/bar_tracking/training/training_images/21321464700.jpg",
        "size": {
            "width": 720,
            "height": 720
        },
        "state": 2,
        "type": 1
    },
    "regions": [
        {
            "id": "mbCXcf5WW",
            "type": "RECTANGLE",
            "tags": [
                "inside_plate"
            ],
            "boundingBox": {
                "height": 141.63009404388714,
                "width": 172.6645768025078,
                "left": 385.67398119122254,
                "top": 578.3699059561128
            },
            "points": [
                {
                    "x": 385.67398119122254,
                    "y": 578.3699059561128
                },
                {
                    "x": 558.3385579937303,
                    "y": 578.3699059561128
                },
                {
                    "x": 558.3385579937303,
                    "y": 719.9999999999999
                },
                {
                    "x": 385.67398119122254,
                    "y": 719.9999999999999
                }
            ]
        },
        {
            "id": "AinunbBFt",
            "type": "RECTANGLE",
            "tags": [
                "outside_plate"
            ],
            "boundingBox": {
                "height": 153.4796238244514,
                "width": 192.41379310344826,
                "left": 62.91536050156739,
                "top": 566.5203761755486
            },
            "points": [
                {
                    "x": 62.91536050156739,
                    "y": 566.5203761755486
                },
                {
                    "x": 255.32915360501565,
                    "y": 566.5203761755486
                },
                {
                    "x": 255.32915360501565,
                    "y": 719.9999999999999
                },
                {
                    "x": 62.91536050156739,
                    "y": 719.9999999999999
                }
            ]
        }
    ],
    "version": "2.2.0"
}