{
    "asset": {
        "format": "jpg",
        "id": "6fb9494f13b0abcacd2784e66f3e313f",
        "name": "76547077800.jpg",
        "path": "file://wsl.localhost/Debian/root/workspace/bar_tracking/training/training_images/76547077800.jpg",
        "size": {
            "width": 720,
            "height": 720
        },
        "state": 2,
        "type": 1
    },
    "regions": [
        {
            "id": "ARagaknxS",
            "type": "RECTANGLE",
            "tags": [
                "inside_plate"
            ],
            "boundingBox": {
                "height": 165.36774193548388,
                "width": 112.41290322580646,
                "left": 553.7032258064517,
                "top": 48.30967741935484
            },
            "points": [
                {
                    "x": 553.7032258064517,
                    "y": 48.30967741935484
                },
                {
                    "x": 666.1161290322581,
                    "y": 48.30967741935484
                },
                {
                    "x": 666.1161290322581,
                    "y": 213.67741935483872
                },
                {
                    "x": 553.7032258064517,
                    "y": 213.67741935483872
                }
            ]
        },
        {
            "id": "0ad7uJgIH",
            "type": "RECTANGLE",
            "tags": [
                "outside_plate"
            ],
            "boundingBox": {
                "height": 176.51612903225808,
                "width": 89.18709677419355,
                "left": 52.02580645161291,
                "top": 0
            },
            "points": [
                {
                    "x": 52.02580645161291,
                    "y": 0
                },
                {
                    "x": 141.21290322580646,
                    "y": 0
                },
                {
                    "x": 141.21290322580646,
                    "y": 176.51612903225808
                },
                {
                    "x": 52.02580645161291,
                    "y": 176.51612903225808
                }
            ]
        }
    ],
    "version": "2.2.0"
}