{
    "asset": {
        "format": "jpg",
        "id": "7f29ecc7ffc3c3c8cee5ba41278001b8",
        "name": "6034121200.jpg",
        "path": "file://wsl.localhost/Debian/root/workspace/bar_tracking/training/training_images/6034121200.jpg",
        "size": {
            "width": 720,
            "height": 720
        },
        "state": 2,
        "type": 1
    },
    "regions": [
        {
            "id": "zDa_ZSIFv",
            "type": "RECTANGLE",
            "tags": [
                "inside_plate"
            ],
            "boundingBox": {
                "height": 153.4796238244514,
                "width": 147.27272727272725,
                "left": 420.6583072100313,
                "top": 114.54545454545453
            },
            "points": [
                {
                    "x": 420.6583072100313,
                    "y": 114.54545454545453
                },
                {
                    "x": 567.9310344827586,
                    "y": 114.54545454545453
                },
                {
                    "x": 567.9310344827586,
                    "y": 268.02507836990594
                },
                {
                    "x": 420.6583072100313,
                    "y": 268.02507836990594
                }
            ]
        },
        {
            "id": "13V7lSR8q",
            "type": "RECTANGLE",
            "tags": [
                "outside_plate"
            ],
            "boundingBox": {
                "height": 160.81504702194357,
                "width": 172.10031347962382,
                "left": 262.66457680250784,
                "top": 0
            },
            "points": [
                {
                    "x": 262.66457680250784,
                    "y": 0
                },
                {
                    "x": 434.7648902821316,
                    "y": 0
                },
                {
                    "x": 434.7648902821316,
                    "y": 160.81504702194357
                },
                {
                    "x": 262.66457680250784,
                    "y": 160.81504702194357
                }
            ]
        }
    ],
    "version": "2.2.0"
}