{
    "asset": {
        "format": "jpg",
        "id": "9124ad4ee68b430cfeef306564074c06",
        "name": "99171308000.jpg",
        "path": "file://wsl.localhost/Debian/root/workspace/bar_tracking/training/training_images/99171308000.jpg",
        "size": {
            "width": 720,
            "height": 720
        },
        "state": 2,
        "type": 1
    },
    "regions": [
        {
            "id": "40X_09rrw",
            "type": "RECTANGLE",
            "tags": [
                "outside_plate"
            ],
            "boundingBox": {
                "height": 176.05015673981188,
                "width": 154.0438871473354,
                "left": 80.40752351097179,
                "top": 326.70846394984324
            },
            "points": [
                {
                    "x": 80.40752351097179,
                    "y": 326.70846394984324
                },
                {
                    "x": 234.4514106583072,
                    "y": 326.70846394984324
                },
                {
                    "x": 234.4514106583072,
                    "y": 502.7586206896551
                },
                {
                    "x": 80.40752351097179,
                    "y": 502.7586206896551
                }
            ]
        },
        {
            "id": "tCDhleZVU",
            "type": "RECTANGLE",
            "tags": [
                "inside_plate"
            ],
            "boundingBox": {
                "height": 150.0940438871473,
                "width": 142.19435736677116,
                "left": 342.7899686520376,
                "top": 310.34482758620686
            },
            "points": [
                {
                    "x": 342.7899686520376,
                    "y": 310.34482758620686
                },
                {
                    "x": 484.98432601880876,
                    "y": 310.34482758620686
                },
                {
                    "x": 484.98432601880876,
                    "y": 460.4388714733542
                },
                {
                    "x": 342.7899686520376,
                    "y": 460.4388714733542
                }
            ]
        }
    ],
    "version": "2.2.0"
}