{
    "asset": {
        "format": "jpg",
        "id": "aaccbca34a71dd2e490a3ad4cc3d8f1b",
        "name": "87318505300.jpg",
        "path": "file://wsl.localhost/Debian/root/workspace/bar_tracking/training/training_images/87318505300.jpg",
        "size": {
            "width": 720,
            "height": 720
        },
        "state": 2,
        "type": 1
    },
    "regions": [
        {
            "id": "e7YUT-G6y",
            "type": "RECTANGLE",
            "tags": [
                "inside_plate"
            ],
            "boundingBox": {
                "height": 156.30094043887146,
                "width": 129.21630094043886,
                "left": 165.04702194357364,
                "top": 12.413793103448274
            },
            "points": [
                {
                    "x": 165.04702194357364,
                    "y": 12.413793103448274
                },
                {
                    "x": 294.2633228840125,
                    "y": 12.413793103448274
                },
                {
                    "x": 294.2633228840125,
                    "y": 168.71473354231972
                },
                {
                    "x": 165.04702194357364,
                    "y": 168.71473354231972
                }
            ]
        },
        {
            "id": "UswoP4zvQ",
            "type": "RECTANGLE",
            "tags": [
                "outside_plate"
            ],
            "boundingBox": {
                "height": 111.15987460815046,
                "width": 132.60188087774293,
                "left": 502.4764890282131,
                "top": 0
            },
            "points": [
                {
                    "x": 502.4764890282131,
                    "y": 0
                },
                {
                    "x": 635.078369905956,
                    "y": 0
                },
                {
                    "x": 635.078369905956,
                    "y": 111.15987460815046
                },
                {
                    "x": 502.4764890282131,
                    "y": 111.15987460815046
                }
            ]
        }
    ],
    "version": "2.2.0"
}