{
    "asset": {
        "format": "jpg",
        "id": "f25ec8c15bc5cfa46b040d22b972516a",
        "name": "116882614100.jpg",
        "path": "file://wsl.localhost/Debian/root/workspace/bar_tracking/training/training_images/116882614100.jpg",
        "size": {
            "width": 720,
            "height": 720
        },
        "state": 2,
        "type": 1
    },
    "regions": [
        {
            "id": "y5FkmHIey",
            "type": "RECTANGLE",
            "tags": [
                "outside_plate"
            ],
            "boundingBox": {
                "height": 271.974921630094,
                "width": 193.8244514106583,
                "left": 0,
                "top": 44.01253918495297
            },
            "points": [
                {
                    "x": 0,
                    "y": 44.01253918495297
                },
                {
                    "x": 193.8244514106583,
                    "y": 44.01253918495297
                },
                {
                    "x": 193.8244514106583,
                    "y": 315.987460815047
                },
                {
                    "x": 0,
                    "y": 315.987460815047
                }
            ]
        },
        {
            "id": "T6fCV8s-Q",
            "type": "RECTANGLE",
            "tags": [
                "inside_plate"
            ],
            "boundingBox": {
                "height": 245.45454545454544,
                "width": 224.57680250783696,
                "left": 377.21003134796234,
                "top": 7.899686520376175
            },
            "points": [
                {
                    "x": 377.21003134796234,
                    "y": 7.899686520376175
                },
                {
                    "x": 601.7868338557993,
                    "y": 7.899686520376175
                },
                {
                    "x": 601.7868338557993,
                    "y": 253.35423197492162
                },
                {
                    "x": 377.21003134796234,
                    "y": 253.35423197492162
                }
            ]
        }
    ],
    "version": "2.2.0"
}