{
    "asset": {
        "format": "jpg",
        "id": "f392fc2f668e114f3e62906df1d6c41a",
        "name": "21298074600.jpg",
        "path": "file://wsl.localhost/Debian/root/workspace/bar_tracking/training/training_images/21298074600.jpg",
        "size": {
            "width": 720,
            "height": 720
        },
        "state": 2,
        "type": 1
    },
    "regions": [
        {
            "id": "bw4C5m8Xd",
            "type": "RECTANGLE",
            "tags": [
                "outside_plate"
            ],
            "boundingBox": {
                "height": 204.38709677419357,
                "width": 167.2258064516129,
                "left": 141.21290322580646,
                "top": 265.7032258064516
            },
            "points": [
                {
                    "x": 141.21290322580646,
                    "y": 265.7032258064516
                },
                {
                    "x": 308.43870967741935,
                    "y": 265.7032258064516
                },
                {
                    "x": 308.43870967741935,
                    "y": 470.0903225806452
                },
                {
                    "x": 141.21290322580646,
                    "y": 470.0903225806452
                }
            ]
        },
        {
            "id": "B3mwbIogq",
            "type": "RECTANGLE",
            "tags": [
                "inside_plate"
            ],
            "boundingBox": {
                "height": 177.4451612903226,
                "width": 170.01290322580647,
                "left": 425.4967741935484,
                "top": 298.2193548387097
            },
            "points": [
                {
                    "x": 425.4967741935484,
                    "y": 298.2193548387097
                },
                {
                    "x": 595.5096774193548,
                    "y": 298.2193548387097
                },
                {
                    "x": 595.5096774193548,
                    "y": 475.6645161290323
                },
                {
                    "x": 425.4967741935484,
                    "y": 475.6645161290323
                }
            ]
        }
    ],
    "version": "2.2.0"
}