{
    "asset": {
        "format": "jpg",
        "id": "f692927a2895287985f92b60a4ac0606",
        "name": "27744953300.jpg",
        "path": "file://wsl.localhost/Debian/root/workspace/bar_tracking/training/training_images/27744953300.jpg",
        "size": {
            "width": 720,
            "height": 720
        },
        "state": 2,
        "type": 1
    },
    "regions": [
        {
            "id": "mkiVzlU4l",
            "type": "RECTANGLE",
            "tags": [
                "outside_plate"
            ],
            "boundingBox": {
                "height": 184.51410658307208,
                "width": 169.27899686520374,
                "left": 130.06269592476488,
                "top": 230.2194357366771
            },
            "points": [
                {
                    "x": 130.06269592476488,
                    "y": 230.2194357366771
                },
                {
                    "x": 299.34169278996865,
                    "y": 230.2194357366771
                },
                {
                    "x": 299.34169278996865,
                    "y": 414.7335423197492
                },
                {
                    "x": 130.06269592476488,
                    "y": 414.7335423197492
                }
            ]
        },
        {
            "id": "ZafqD0p5C",
            "type": "RECTANGLE",
            "tags": [
                "inside_plate"
            ],
            "boundingBox": {
                "height": 154.60815047021939,
                "width": 138.80877742946709,
                "left": 384.54545454545445,
                "top": 284.9529780564263
            },
            "points": [
                {
                    "x": 384.54545454545445,
                    "y": 284.9529780564263
                },
                {
                    "x": 523.3542319749215,
                    "y": 284.9529780564263
                },
                {
                    "x": 523.3542319749215,
                    "y": 439.5611285266457
                },
                {
                    "x": 384.54545454545445,
                    "y": 439.5611285266457
                }
            ]
        }
    ],
    "version": "2.2.0"
}